pantoufle_tree_sitter_languages-1.6.0.dist-info/METADATA
pantoufle_tree_sitter_languages-1.6.0.dist-info/LICENSE
pantoufle_tree_sitter_languages-1.6.0.dist-info/WHEEL
pantoufle_tree_sitter_languages-1.6.0.dist-info/RECORD
pantoufle_tree_sitter_languages-1.6.0.dist-info/top_level.txt
pantoufle_tree_sitter_languages.libs/libgcc_s-a04fdf82.so.1
pantoufle_tree_sitter_languages.libs/libstdc++-a9383cce.so.6.0.28
tree_sitter_languages/core.cpython-311-x86_64-linux-musl.so
tree_sitter_languages/__init__.py
tree_sitter_languages/languages.so
